{
 "charts": [],
 "content": "[{\"id\":\"RMsPeY-t3P\",\"type\":\"header\",\"data\":{\"text\":\"<span class=\\\"h4\\\">VCM ERP Reports</span>\",\"col\":12}},{\"id\":\"Kvo4-Cw-Km\",\"type\":\"card\",\"data\":{\"card_name\":\"POS Reports\",\"col\":4}},{\"id\":\"TmLSRwO6r1\",\"type\":\"card\",\"data\":{\"card_name\":\"Customer and Supplier Reports\",\"col\":4}},{\"id\":\"UbrbU-sWwA\",\"type\":\"card\",\"data\":{\"card_name\":\"Item wise Reports\",\"col\":4}},{\"id\":\"K98bX1Y5o6\",\"type\":\"card\",\"data\":{\"card_name\":\"MRN and GRN Releated Reports\",\"col\":4}},{\"id\":\"6qYFUPGjv9\",\"type\":\"card\",\"data\":{\"card_name\":\"Purchase Reports\",\"col\":4}},{\"id\":\"OfGCKG-Lv1\",\"type\":\"card\",\"data\":{\"card_name\":\"Stock Report\",\"col\":4}},{\"id\":\"jqkc1jLuaH\",\"type\":\"card\",\"data\":{\"card_name\":\"Other Reports\",\"col\":4}},{\"id\":\"1p7HfGtlSS\",\"type\":\"card\",\"data\":{\"card_name\":\"Finance Reports\",\"col\":4}},{\"id\":\"DjVNLNCCcC\",\"type\":\"shortcut\",\"data\":{\"shortcut_name\":\"VCM POS Sales Dashboard\",\"col\":3}}]",
 "creation": "2025-01-17 10:59:18.706177",
 "custom_blocks": [],
 "docstatus": 0,
 "doctype": "Workspace",
 "for_user": "",
 "hide_custom": 0,
 "icon": "solid-success",
 "idx": 0,
 "indicator_color": "green",
 "is_hidden": 0,
 "label": "VCM ERP",
 "links": [
  {
   "hidden": 0,
   "is_query_report": 0,
   "label": "Customer and Supplier Reports",
   "link_count": 3,
   "link_type": "DocType",
   "onboard": 0,
   "type": "Card Break"
  },
  {
   "hidden": 0,
   "is_query_report": 1,
   "label": "Supplier Ledger Summary",
   "link_count": 0,
   "link_to": "Supplier Ledger Summary",
   "link_type": "Report",
   "onboard": 1,
   "type": "Link"
  },
  {
   "hidden": 0,
   "is_query_report": 1,
   "label": "Customer Credit Balance",
   "link_count": 0,
   "link_to": "Customer Credit Balance",
   "link_type": "Report",
   "onboard": 1,
   "type": "Link"
  },
  {
   "hidden": 0,
   "is_query_report": 1,
   "label": "Customer Ledger Summary",
   "link_count": 0,
   "link_to": "Customer Ledger Summary",
   "link_type": "Report",
   "onboard": 1,
   "type": "Link"
  },
  {
   "hidden": 0,
   "is_query_report": 0,
   "label": "Item wise Reports",
   "link_count": 5,
   "link_type": "DocType",
   "onboard": 0,
   "type": "Card Break"
  },
  {
   "hidden": 0,
   "is_query_report": 1,
   "label": "Item Prices",
   "link_count": 0,
   "link_to": "Item Prices",
   "link_type": "Report",
   "onboard": 1,
   "type": "Link"
  },
  {
   "hidden": 0,
   "is_query_report": 1,
   "label": "Item-wise Sales Register",
   "link_count": 0,
   "link_to": "Item-wise Sales Register",
   "link_type": "Report",
   "onboard": 1,
   "type": "Link"
  },
  {
   "hidden": 0,
   "is_query_report": 1,
   "label": "Item-wise Price List Rate",
   "link_count": 0,
   "link_to": "Item-wise Price List Rate",
   "link_type": "Report",
   "onboard": 1,
   "type": "Link"
  },
  {
   "hidden": 0,
   "is_query_report": 1,
   "label": "ITEM With GST Rate and HSN",
   "link_count": 0,
   "link_to": "ITEM With GST Rate and HSN",
   "link_type": "Report",
   "onboard": 1,
   "type": "Link"
  },
  {
   "hidden": 0,
   "is_query_report": 1,
   "label": "Item Balance (Simple)",
   "link_count": 0,
   "link_to": "Item Balance (Simple)",
   "link_type": "Report",
   "onboard": 1,
   "type": "Link"
  },
  {
   "hidden": 0,
   "is_query_report": 0,
   "label": "MRN and GRN Releated Reports",
   "link_count": 4,
   "link_type": "DocType",
   "onboard": 0,
   "type": "Card Break"
  },
  {
   "hidden": 0,
   "is_query_report": 1,
   "label": "Requested Items to Order and Receive",
   "link_count": 0,
   "link_to": "Requested Items to Order and Receive",
   "link_type": "Report",
   "onboard": 1,
   "type": "Link"
  },
  {
   "hidden": 0,
   "is_query_report": 1,
   "label": "Material Requests for which Supplier Quotations are not created",
   "link_count": 0,
   "link_to": "Material Requests for which Supplier Quotations are not created",
   "link_type": "Report",
   "onboard": 1,
   "type": "Link"
  },
  {
   "hidden": 0,
   "is_query_report": 1,
   "label": "Purchase Receipt Trends",
   "link_count": 0,
   "link_to": "Purchase Receipt Trends",
   "link_type": "Report",
   "onboard": 1,
   "type": "Link"
  },
  {
   "hidden": 0,
   "is_query_report": 1,
   "label": "VCM MR Tracker",
   "link_count": 0,
   "link_to": "VCM MR Tracker",
   "link_type": "Report",
   "onboard": 1,
   "type": "Link"
  },
  {
   "hidden": 0,
   "is_query_report": 0,
   "label": "Finance Reports",
   "link_count": 9,
   "link_type": "DocType",
   "onboard": 0,
   "type": "Card Break"
  },
  {
   "hidden": 0,
   "is_query_report": 1,
   "label": "COGS By Item Group",
   "link_count": 0,
   "link_to": "COGS By Item Group",
   "link_type": "Report",
   "onboard": 1,
   "type": "Link"
  },
  {
   "hidden": 0,
   "is_query_report": 1,
   "label": "Consolidated Financial Statement",
   "link_count": 0,
   "link_to": "Consolidated Financial Statement",
   "link_type": "Report",
   "onboard": 1,
   "type": "Link"
  },
  {
   "hidden": 0,
   "is_query_report": 1,
   "label": "Gross and Net Profit Report",
   "link_count": 0,
   "link_to": "Gross and Net Profit Report",
   "link_type": "Report",
   "onboard": 1,
   "type": "Link"
  },
  {
   "hidden": 0,
   "is_query_report": 1,
   "label": "Sales Register",
   "link_count": 0,
   "link_to": "Sales Register",
   "link_type": "Report",
   "onboard": 1,
   "type": "Link"
  },
  {
   "hidden": 0,
   "is_query_report": 1,
   "label": "Trial Balance",
   "link_count": 0,
   "link_to": "Trial Balance",
   "link_type": "Report",
   "onboard": 1,
   "type": "Link"
  },
  {
   "hidden": 0,
   "is_query_report": 1,
   "label": "Profitability Analysis",
   "link_count": 0,
   "link_to": "Profitability Analysis",
   "link_type": "Report",
   "onboard": 1,
   "type": "Link"
  },
  {
   "hidden": 0,
   "is_query_report": 1,
   "label": "Gross Profit",
   "link_count": 0,
   "link_to": "Gross Profit",
   "link_type": "Report",
   "onboard": 1,
   "type": "Link"
  },
  {
   "hidden": 0,
   "is_query_report": 1,
   "label": "Profit and Loss Statement",
   "link_count": 0,
   "link_to": "Profit and Loss Statement",
   "link_type": "Report",
   "onboard": 1,
   "type": "Link"
  },
  {
   "hidden": 0,
   "is_query_report": 0,
   "label": "VCM General Ledger",
   "link_count": 0,
   "link_to": "VCM General Ledger",
   "link_type": "Report",
   "onboard": 1,
   "report_ref_doctype": "GL Entry",
   "type": "Link"
  },
  {
   "hidden": 0,
   "is_query_report": 0,
   "label": "Purchase Reports",
   "link_count": 6,
   "link_type": "DocType",
   "onboard": 0,
   "type": "Card Break"
  },
  {
   "hidden": 0,
   "is_query_report": 1,
   "label": "Purchase Register",
   "link_count": 0,
   "link_to": "Purchase Register",
   "link_type": "Report",
   "onboard": 1,
   "type": "Link"
  },
  {
   "hidden": 0,
   "is_query_report": 1,
   "label": "Item-wise Purchase Register",
   "link_count": 0,
   "link_to": "Item-wise Purchase Register",
   "link_type": "Report",
   "onboard": 1,
   "type": "Link"
  },
  {
   "hidden": 0,
   "is_query_report": 1,
   "label": "Item-wise Purchase History",
   "link_count": 0,
   "link_to": "Item-wise Purchase History",
   "link_type": "Report",
   "onboard": 1,
   "type": "Link"
  },
  {
   "hidden": 0,
   "is_query_report": 1,
   "label": "Purchase Order Analysis",
   "link_count": 0,
   "link_to": "Purchase Order Analysis",
   "link_type": "Report",
   "onboard": 1,
   "type": "Link"
  },
  {
   "hidden": 0,
   "is_query_report": 1,
   "label": "Accounts Payable",
   "link_count": 0,
   "link_to": "Accounts Payable",
   "link_type": "Report",
   "onboard": 1,
   "type": "Link"
  },
  {
   "hidden": 0,
   "is_query_report": 1,
   "label": "Procurement Tracker",
   "link_count": 0,
   "link_to": "Procurement Tracker",
   "link_type": "Report",
   "onboard": 1,
   "type": "Link"
  },
  {
   "hidden": 0,
   "is_query_report": 0,
   "label": "Stock Report",
   "link_count": 9,
   "link_type": "DocType",
   "onboard": 0,
   "type": "Card Break"
  },
  {
   "hidden": 0,
   "is_query_report": 1,
   "label": "Total Stock Summary",
   "link_count": 0,
   "link_to": "Total Stock Summary",
   "link_type": "Report",
   "onboard": 1,
   "type": "Link"
  },
  {
   "hidden": 0,
   "is_query_report": 1,
   "label": "Stock Ledger Variance",
   "link_count": 0,
   "link_to": "Stock Ledger Variance",
   "link_type": "Report",
   "onboard": 1,
   "type": "Link"
  },
  {
   "hidden": 0,
   "is_query_report": 1,
   "label": "Stock Ledger",
   "link_count": 0,
   "link_to": "Stock Ledger",
   "link_type": "Report",
   "onboard": 1,
   "type": "Link"
  },
  {
   "hidden": 0,
   "is_query_report": 1,
   "label": "Stock Balance",
   "link_count": 0,
   "link_to": "Stock Balance",
   "link_type": "Report",
   "onboard": 1,
   "type": "Link"
  },
  {
   "hidden": 0,
   "is_query_report": 1,
   "label": "Total Stock Summary - Gifts and Books",
   "link_count": 0,
   "link_to": "Total Stock Summary - Gifts and Books",
   "link_type": "Report",
   "onboard": 1,
   "type": "Link"
  },
  {
   "hidden": 0,
   "is_query_report": 1,
   "label": "Billed Items To Be Received",
   "link_count": 0,
   "link_to": "Billed Items To Be Received",
   "link_type": "Report",
   "onboard": 1,
   "type": "Link"
  },
  {
   "hidden": 0,
   "is_query_report": 1,
   "label": "Warehouse Wise Stock Balance",
   "link_count": 0,
   "link_to": "Warehouse Wise Stock Balance",
   "link_type": "Report",
   "onboard": 1,
   "type": "Link"
  },
  {
   "hidden": 0,
   "is_query_report": 1,
   "label": "Warehouse Sales & Stock Analysis",
   "link_count": 0,
   "link_to": "Warehouse Sales & Stock Analysis",
   "link_type": "Report",
   "onboard": 1,
   "type": "Link"
  },
  {
   "hidden": 0,
   "is_query_report": 1,
   "label": "Warehouse wise Item Balance Age and Value",
   "link_count": 0,
   "link_to": "Warehouse wise Item Balance Age and Value",
   "link_type": "Report",
   "onboard": 1,
   "type": "Link"
  },
  {
   "hidden": 0,
   "is_query_report": 0,
   "label": "Other Reports",
   "link_count": 4,
   "link_type": "DocType",
   "onboard": 0,
   "type": "Card Break"
  },
  {
   "hidden": 0,
   "is_query_report": 1,
   "label": "GST Itemised Purchase Register",
   "link_count": 0,
   "link_to": "GST Itemised Purchase Register",
   "link_type": "Report",
   "onboard": 1,
   "type": "Link"
  },
  {
   "hidden": 0,
   "is_query_report": 1,
   "label": "GST Sales Register",
   "link_count": 0,
   "link_to": "GST Sales Register",
   "link_type": "Report",
   "onboard": 1,
   "type": "Link"
  },
  {
   "hidden": 0,
   "is_query_report": 1,
   "label": "GST Purchase Register",
   "link_count": 0,
   "link_to": "GST Purchase Register",
   "link_type": "Report",
   "onboard": 1,
   "type": "Link"
  },
  {
   "hidden": 0,
   "is_query_report": 1,
   "label": "GST Itemised Sales Register",
   "link_count": 0,
   "link_to": "GST Itemised Sales Register",
   "link_type": "Report",
   "onboard": 1,
   "type": "Link"
  },
  {
   "hidden": 0,
   "is_query_report": 0,
   "label": "POS Reports",
   "link_count": 6,
   "link_type": "DocType",
   "onboard": 0,
   "type": "Card Break"
  },
  {
   "hidden": 0,
   "is_query_report": 1,
   "label": "POS Register",
   "link_count": 0,
   "link_to": "POS Register",
   "link_type": "Report",
   "onboard": 1,
   "type": "Link"
  },
  {
   "hidden": 0,
   "is_query_report": 1,
   "label": "POS Closing Entry",
   "link_count": 0,
   "link_to": "POS Closing Entry",
   "link_type": "DocType",
   "onboard": 1,
   "type": "Link"
  },
  {
   "hidden": 0,
   "is_query_report": 1,
   "label": "POS Register - Gifts and Books",
   "link_count": 0,
   "link_to": "POS Register - Gifts and Books",
   "link_type": "Report",
   "onboard": 1,
   "type": "Link"
  },
  {
   "hidden": 0,
   "is_query_report": 0,
   "label": "Sales Rep Performance",
   "link_count": 0,
   "link_to": "Sales Rep Performance",
   "link_type": "Report",
   "onboard": 1,
   "report_ref_doctype": "POS Invoice",
   "type": "Link"
  },
  {
   "hidden": 0,
   "is_query_report": 1,
   "label": "VCM Mode of Payment & Top Performing Items",
   "link_count": 0,
   "link_to": "VCM Mode of Payment & Top Performing Items",
   "link_type": "Report",
   "onboard": 0,
   "type": "Link"
  },
  {
   "hidden": 0,
   "is_query_report": 1,
   "label": "VCM Sales Comparison",
   "link_count": 0,
   "link_to": "VCM Sales Comparison",
   "link_type": "Report",
   "onboard": 0,
   "type": "Link"
  }
 ],
 "modified": "2025-03-18 16:18:45.475964",
 "modified_by": "Administrator",
 "module": "erpnext_vcm",
 "name": "VCM ERP",
 "number_cards": [],
 "owner": "Administrator",
 "parent_page": "",
 "public": 1,
 "quick_lists": [],
 "roles": [],
 "sequence_id": 40.0,
 "shortcuts": [
  {
   "color": "Grey",
   "doc_view": "List",
   "label": "VCM POS Sales Dashboard",
   "link_to": "VCM Sales Dashboard",
   "type": "Dashboard"
  }
 ],
 "title": "VCM ERP"
}